openground_sdk/__init__.py
openground_sdk/openground.py
openground_sdk-0.0.11.dist-info/licenses/LICENSE
openground_sdk_auth/__init__.py
openground_sdk_auth/authentication.py
openground_sdk_auth/callback.html
openground_sdk-0.0.11.dist-info/METADATA
openground_sdk-0.0.11.dist-info/WHEEL
openground_sdk-0.0.11.dist-info/top_level.txt
openground_sdk-0.0.11.dist-info/RECORD
